kelp/__init__.py
kelp/kelp.py
klp-0.0.0.dist-info/LICENSE
klp-0.0.0.dist-info/METADATA
klp-0.0.0.dist-info/WHEEL
klp-0.0.0.dist-info/entry_points.txt
klp-0.0.0.dist-info/top_level.txt
klp-0.0.0.dist-info/RECORD
