Metadata-Version: 2.1
Name: klp
Version: 0.0.0
Summary: Python replacement for homebrew
Home-page: https://github.com/crhuber/kelp
Author: crhuber
Author-email: crhuber@example.com
Maintainer: crhuber
Maintainer-email: crhuber@example.com
License: Apache License, Version 2.0
Platform: UNKNOWN
Classifier: Development Status :: 5 - Production/Stable
Classifier: Environment :: Console
Classifier: Intended Audience :: Developers
Classifier: License :: OSI Approved :: Apache Software License
Classifier: Programming Language :: Python
Classifier: Programming Language :: Python :: 3.7
Classifier: Programming Language :: Python :: 3.8
Requires-Python: >=3.7
Requires-Dist: requests (==2.22.0)
Requires-Dist: Click (==7.0)
Requires-Dist: filetype (==1.0.5)
